jupyter_scdg_viewer_widget-0.1.1.data/data/etc/jupyter/nbconfig/notebook.d/scdg-viewer.json
jupyter_scdg_viewer_widget-0.1.1.data/data/share/jupyter/nbextensions/scdg-viewer/extension.js
jupyter_scdg_viewer_widget-0.1.1.data/data/share/jupyter/nbextensions/scdg-viewer/index.js
jupyter_scdg_viewer_widget-0.1.1.data/data/share/jupyter/nbextensions/scdg-viewer/index.js.map
scdgviewer/__init__.py
scdgviewer/_version.py
scdgviewer/scdgviewer.py
scdgviewer/static/extension.js
scdgviewer/static/index.js
scdgviewer/static/index.js.map
jupyter_scdg_viewer_widget-0.1.1.dist-info/METADATA
jupyter_scdg_viewer_widget-0.1.1.dist-info/WHEEL
jupyter_scdg_viewer_widget-0.1.1.dist-info/top_level.txt
jupyter_scdg_viewer_widget-0.1.1.dist-info/RECORD
