Metadata-Version: 2.1
Name: jupyter-scdg-viewer-widget
Version: 0.1.1
Summary: A Jupyter SCDG Viewer Widget
Home-page: UNKNOWN
Author: Mathieu SIMON
Author-email: mathieu.simon@inria.fr
License: UNKNOWN
Keywords: ipython,jupyter,widgets,scdg,graph
Platform: UNKNOWN
Classifier: Development Status :: 4 - Beta
Classifier: License :: OSI Approved
Classifier: Framework :: Jupyter
Classifier: Intended Audience :: Developers
Classifier: Intended Audience :: Science/Research
Classifier: Topic :: Multimedia :: Graphics
Classifier: Programming Language :: Python :: 3
Classifier: Programming Language :: Python :: 3.3
Classifier: Programming Language :: Python :: 3.4
Classifier: Programming Language :: Python :: 3.5
Classifier: Programming Language :: Python :: 3.6
Requires-Dist: ipywidgets (>=7.0.0)
Requires-Dist: vis
